README.txt
setup.py
canteen/__init__.py
canteen/__main__.py
canteen/dispatch.py
canteen/exceptions.py
canteen/setup.py
canteen/test.py
canteen.egg-info/PKG-INFO
canteen.egg-info/SOURCES.txt
canteen.egg-info/dependency_links.txt
canteen.egg-info/requires.txt
canteen.egg-info/top_level.txt
canteen.egg-info/zip-safe
canteen/base/__init__.py
canteen/base/handler.py
canteen/base/logic.py
canteen/base/page.py
canteen/base/protocol.py
canteen/core/__init__.py
canteen/core/hooks.py
canteen/core/injection.py
canteen/core/meta.py
canteen/core/runtime.py
canteen/logic/__init__.py
canteen/logic/assets.py
canteen/logic/cache.py
canteen/logic/realtime.py
canteen/logic/session.py
canteen/logic/template.py
canteen/logic/http/__init__.py
canteen/logic/http/agent.py
canteen/logic/http/cookies.py
canteen/logic/http/semantics.py
canteen/model/__init__.py
canteen/model/exceptions.py
canteen/model/query.py
canteen/model/adapter/__init__.py
canteen/model/adapter/abstract.py
canteen/model/adapter/core.py
canteen/model/adapter/inmemory.py
canteen/model/adapter/protorpc.py
canteen/model/adapter/redis.py
canteen/rpc/__init__.py
canteen/rpc/exceptions.py
canteen/rpc/protocol/__init__.py
canteen/rpc/protocol/json.py
canteen/rpc/protocol/msgpack.py
canteen/runtime/__init__.py
canteen/runtime/uwsgi.py
canteen/runtime/werkzeug.py
canteen/runtime/wsgiref.py
canteen/util/__init__.py
canteen/util/cli.py
canteen/util/config.py
canteen/util/debug.py
canteen/util/decorators.py
canteen/util/struct.py
canteen_tests/__init__.py
canteen_tests/__main__.py
canteen_tests/test__init__.py
canteen_tests/test_dispatch.py
canteen_tests/test_setup.py
canteen_tests/test_test.py
canteen_tests/test_adapters/__init__.py
canteen_tests/test_adapters/test_abstract.py
canteen_tests/test_adapters/test_inmemory.py
canteen_tests/test_adapters/test_protorpc.py
canteen_tests/test_adapters/test_redis.py
canteen_tests/test_base/__init__.py
canteen_tests/test_base/test_handler.py
canteen_tests/test_base/test_logic.py
canteen_tests/test_base/test_page.py
canteen_tests/test_base/test_protocol.py
canteen_tests/test_core/__init__.py
canteen_tests/test_core/test_hooks.py
canteen_tests/test_core/test_injection.py
