Metadata-Version: 1.0
Name: canteen
Version: 0.4-alpha
Summary: Minimally complicated, maximally blasphemous approach to Python development
Home-page: https://github.com/sgammon/canteen
Author: Sam Gammon
Author-email: sam@momentum.io
License: UNKNOWN
Platform: UNKNOWN
